{"author":"程之才","id":186821,"strains":["平平仄平仄，仄平仄仄平。","○平仄仄○，仄仄平仄平。","○平仄平仄，仄仄仄仄平。","仄平仄平仄，仄仄平平平。","平平仄○○，平仄仄仄平。","○平仄仄仄，仄仄仄平平。","仄平平仄○，仄仄仄仄平。","仄仄平仄仄，平平仄平平。","○仄仄仄平，仄仄平平平。","平平仄仄仄，平平仄仄平。","平平仄仄平，平仄仄仄平。","平平仄仄仄，仄仄平平平。","○○平平仄，仄○仄仄○。","平平仄平仄，仄仄仄平平。","仄仄仄平平，仄仄仄仄平。","○平仄仄仄，仄仄平平平。"],"paragraphs":["名因物之累，物尝不厌名。","标之曰到难，日有车马声。","苍崖匪才凿，洞室百步宏。","潜龙想鳞鬣，石乳悬旒缨。","溪流湛其中，吞吐日月精。","其源咫尺耳，盥濯未尝经。","我来先振衣，色变水石清。","倚杖聊四顾，高低古今铭。","颇恨辙迹多，不益云萝情。","西南有复岭，烟霞昼晦冥。","呼僧指问之，山外或小平。","茅茨构石壁，兔鹿浑微生。","沈吟幽栖地，雅兴宿志并。","何时一椽屋，散髪入岩坰。","脱略五千言，坐忘六尺形。","看云会所适，以此休余龄。"],"title":"碧落洞"}
