{"author":"沈辽","id":189662,"strains":["平仄平平仄仄平，仄平仄仄仄仄○。","仄平○仄仄平○，仄仄仄仄仄仄平。","平平平平平平平，平平仄仄平仄平。","仄平仄仄平仄平，仄○仄仄仄平平。","平平平平仄平平，平○平仄平仄平。","仄平仄仄仄仄平，平平仄仄平仄平。","平仄仄仄○平平，仄平仄仄仄平平。","平平平平仄平平，仄仄仄平平仄平。","仄仄平平仄仄平，仄仄仄平平仄平。","仄仄仄仄平仄平，仄仄平平○仄平。","平平仄仄平平平，仄仄平仄平仄平。","○平仄平仄平平，平平○平仄平平。","仄仄平仄平平平，仄仄○○平平平。","平平仄平仄○平，○仄平仄平平平。","平仄仄仄○平○，仄仄仄平仄平○。"],"paragraphs":["天竺山前十亩园，老夫久种彼土缘。","草堂和尚指初禅，辩净二士立我前。","光明琉璃真金仙，修持内外常湛然。","此心不转今十年，手中一炷紫檀烟。","孤峰飞来自西天，山间花木非世妍。","彼诸佛子忘盖纒，吾知此地为敬田。","师子血乳如流泉，老夫废斥去湘川。","归来江南已华颠，邂逅道人双足纒。","历访名山不惮烦，始自赤城沧海边。","一带复济扬子川，直上锺山长榻眠。","南来不下泾溪船，步至秋浦方息肩。","将穷祖山上淮壖，庐峰胜游想翩翩。","顶上终不巢乌鸢，亦不教观谈偏圆。","公卿贵人喜相延，三尺枯木挥朱弦。","人问佛意如何弹，此曲寂寥少人传。"],"title":"奉送眀雅师"}
