{"190296":"和陶掾见寄","190295":"见省符知有代官一首","190294":"雨后","190293":"公闲念诗社之废寄陶贾二同僚一首","190292":"贾庆甫以局事乘小船犯风波感其危而为诗且以相示仆亦于舟字韵和呈其卒章盖言有俟以慰贤劳之叹也","190291":"贾中甫送庆甫弟来尉永兴久之告归仆多其来而重其去乃为诗以送之","190290":"司马南楼纳凉","190299":"秋日即事呈同僚","190298":"陶掾书斋小饮","190297":"待拒霜开一首","190274":"咏水","190273":"咏萤","190272":"十六夜","190271":"十五夜","190270":"八月十四日夜月","190279":"咏草","190278":"再贶诗复以前韵答之","190277":"谢董都官见寄","190276":"残灯","190275":"咏竹","190285":"黄河","190284":"汴河","190283":"秋怀","190282":"翦刀","190281":"仙掌峰","190280":"闻新雁","190289":"习曹何君屡有引年之语而未暇请今兹官满解去骧作诗言其荣以壮其志惟僚友不异幸同辞以助之","190288":"次韵和聂充甫冬晓初起","190287":"东庵院","190286":"和聂充甫晨霜","190252":"初入淮上","190494":"和新竹","190251":"归兴","190493":"予莅制济民药朱尉掌粜常平粟因以记","190250":"汴上榆柳","190492":"偶作","190491":"自和","190490":"晓出候按察","190259":"过七里泷","190258":"过桐庐县","190257":"驻轩亭","190499":"双莲二首  其二","190256":"将赴富川","190498":"双莲二首  其一","190255":"感梦","190497":"送刘睦州移京西漕","190254":"骧每恶晏起强酒二癖因作诗自警","190496":"和独钓  其二","190253":"自守","190495":"和独钓  其一","190263":"五月到官七月八日始并得家问二","190262":"和访古","190261":"和公余言怀","190260":"和红蕉","190269":"厅前丛竹","190268":"和苦吟二首  其二","190267":"和苦吟二首  其一","190266":"和董公肃十日菊二首  其二","190265":"和董公肃十日菊二首  其一","190264":"红文苋","190239":"酷暑初夜","190230":"谢太守惠家园瓜","190472":"和长道候使者宿龙窟见寄","190471":"回长道中论","190470":"席间和向辟之元夜  其二","190238":"送浦倅之阙","190237":"八月泛江送客","190479":"同长道游惠僧翠樾堂","190236":"萧洒参军宇六首  其六","190478":"和长道交道驿见招同趋府","190235":"萧洒参军宇六首  其五","190477":"探得海棠送章仲成","190234":"萧洒参军宇六首  其四","190476":"送章郎中赴阙  其二","190233":"萧洒参军宇六首  其三","190475":"送章郎中赴阙  其一","190232":"萧洒参军宇六首  其二","190474":"和见贻","190231":"萧洒参军宇六首  其一","190473":"长道将罢邑借前韵以寄","190241":"望","190483":"和朱尉首夏偶书见寄","190240":"十月","190482":"林沼春归后","190481":"四月一日西池作","190480":"清明雨","190249":"舟晚行","190248":"小饮楼上作","190247":"初上汴舟思归","190489":"送王学士赴京东漕","190246":"塞上","190488":"端午雨饮伯英池馆","190245":"残春  其二","190487":"和初夏雨中","190244":"残春  其一","190486":"同朱尉游普宁僧舍","190243":"再和","190485":"和伯英再赋","190242":"和吴常甫移石","190484":"游金柱观瀑泉","19067":"观曹寿卿上舍诗轴题其后  其二","19066":"观曹寿卿上舍诗轴题其后  其一","19069":"戏德秀几道","19068":"旅中有感复用前韵","19063":"次韵梅花四首  其三","19062":"次韵梅花四首  其二","19065":"次韵刘敷言新雁","19064":"次韵梅花四首  其四","19061":"次韵梅花四首  其一","19060":"白菊","190906":"咏素扇","190905":"咏马","190904":"春阴","190903":"春寒","19078":"挽张世英母夫人","190902":"雁屏","19077":"挽提干赵君","190901":"风琴","190900":"自宝丰镇移红蕉于永阳后圃","19079":"岩桂饷郑舜举戏笔代柬  其一","19074":"戏题酒肆","19073":"戏效连珠叠韵体","19076":"挽处士乔公","19075":"夜雪","19070":"使君馈食戏少蒙教授","190909":"投壶格","19072":"偶书","190908":"桔橰","19071":"还余朝纲杂编","190907":"火箸","19049":"谢汪汝平送酒","19048":"次韵刘伯瑞觅酒","19045":"次韵","19044":"客舍久雨无酒戏柬沈泰叔","19047":"次韵陈季陵觅酒二首  其二","19046":"次韵陈季陵觅酒二首  其一","19041":"次韵喜雨","19040":"次韵喜雨兼简彝老","19043":"次韵陈季陵主簿秋雨","19042":"次韵陶几道喜雨","19059":"次韵苏守金橘","19056":"别墅芍药盛开沈公辟有诗见嘲次韵代柬  其二","19055":"别墅芍药盛开沈公辟有诗见嘲次韵代柬  其一","19058":"艾以诸公雌黄其诗意殊不平戏用前韵","19057":"次韵艾慎机县庠蕉花","19052":"再用前韵三首  其一","19051":"汝平诸公见和复用韵二首  其二","19054":"再用前韵三首  其三","19053":"再用前韵三首  其二","19050":"汝平诸公见和复用韵二首  其一","19027":"又次韵冯文度春晚二首  其二","19026":"又次韵冯文度春晚二首  其一","19029":"再过绣川驿","19028":"题义乌县绣川驿","19023":"高师鲁以诗求鹤膝杖且有诗坛寻盟之语戏次其韵  其一","19022":"王有之见和复用韵二首  其二","19025":"客舍春晚","19024":"高师鲁以诗求鹤膝杖且有诗坛寻盟之语戏次其韵  其二","19021":"王有之见和复用韵二首  其一","19020":"立春日有感","190098":"中秋","190097":"窃闻子瞻学士昨日飘然单乘独出南屏旋至北山穷幽览胜真得物外自适之趣邠尝从欧阳公诗云使君厌骑从车马留山前行歌招野叟共步青林间然明公今日之乐正得于此因成诗一章上寄","190096":"簪屣","190095":"早发湖口宿道傍山寺","190094":"谢王介甫见寄","190093":"句  其一八","190092":"句  其一七","190091":"句  其一六","190099":"月","19038":"次韵李元老柬王令周簿喜雨  其二","19037":"次韵李元老柬王令周簿喜雨  其一","19039":"次韵马仲元推官贺五马喜雨","19034":"再次韵  其一","19033":"甲子岁除一夕梦与先子论诗有云未能免俗犹听谶无计为生只送穷此吾顷年诗也汝亦得之否某曰已在家集中既觉泣书二章  其二","19036":"庚申日戏题","19035":"再次韵  其二","19030":"永嘉旅中","19032":"甲子岁除一夕梦与先子论诗有云未能免俗犹听谶无计为生只送穷此吾顷年诗也汝亦得之否某曰已在家集中既觉泣书二章  其一","19031":"盛暑宿集福院晚风雨大作","19009":"代上时相生辰  其二","19016":"上梁尚书生辰  其三","19015":"上梁尚书生辰  其二","19018":"陈镇江生辰  其二","19017":"陈镇江生辰  其一","19012":"钱使君知原生辰  其一","19011":"代上时相生辰  其四","19014":"上梁尚书生辰  其一","19013":"钱使君知原生辰  其二","190090":"句  其一五","19010":"代上时相生辰  其三","19019":"陈镇江生辰  其三","190089":"句  其一四","190088":"句  其一三","190619":"再用前韵和孙正甫所示","190618":"荆林道中示孙张二君","190617":"寄元真州","190859":"琅邪三十二咏 翠微亭","190616":"紫荆花","190858":"琅邪三十二咏 净镜亭","190615":"次韵和邓德夫再和书怀别用三十韵","190857":"琅邪三十二咏 长松迳","190614":"春杪书怀三十韵呈同事邓令","190856":"琅邪三十二咏 琅邪山门","190613":"再用前韵为感春喜会二首酬德夫  其二","190855":"海陵按事","190612":"再用前韵为感春喜会二首酬德夫  其一","190854":"谢简夫太博惠茶","190611":"上巳日赣川忆东湖  其二","190853":"行赴云门驿","190610":"上巳日赣川忆东湖  其一","190852":"别铅山杨公济","190851":"龟峰  其二","190850":"龟峰  其一","190629":"登蓬莱阁","190628":"和淮阳颜长道见寄","190627":"闻潮","190869":"琅邪三十二咏 御书阁","190626":"将至登州","190868":"琅邪三十二咏 开化寺","190625":"九月二十二日黄县道中遇雪","190867":"琅邪三十二咏 回马岭","1909":"缘识  其三八","190624":"再和孙正甫音字韵呈舍人","1908":"缘识  其三七","190866":"琅邪三十二咏 琅邪山","190623":"出东莱城示海傍观者","1907":"缘识  其三六","190865":"琅邪三十二咏 石流渠","1906":"缘识  其三五","190622":"九月十八夜宿莱州海庙夜分登亭望月观海呈伯温舍人","190864":"琅邪三十二咏 班春亭","1905":"缘识  其三四","190621":"再用前韵谢和诗二首","190863":"琅邪三十二咏 逊泉","1904":"缘识  其三三","190620":"胶水道中逢九日呈温伯舍人","190862":"琅邪三十二咏 薛老桥","1903":"缘识  其三二","190861":"琅邪三十二咏 醉翁亭","1902":"缘识  其三一","190860":"琅邪三十二咏 白云亭","1901":"缘识  其三○","190839":"宿坛石驿六首  其四","190838":"宿坛石驿六首  其三","190837":"宿坛石驿六首  其二","190836":"宿坛石驿六首  其一","190835":"阐阳驿观中秋月","190834":"落日","190833":"过查林","190832":"忆后城覧秀亭登望","190831":"感怀","190830":"思侍","190609":"复假前韵为即事二诗且言别于卒章  其二","190608":"复假前韵为即事二诗且言别于卒章  其一","190607":"次韵社日且以善谑","190849":"又和答并叙别","190606":"惜春  其二","190848":"再答和篇","190605":"惜春  其一","190847":"饶守游晋老席上偶成","190604":"次韵德夫推院有感","190846":"中秋十八夜雨望月阻兴","190603":"讯鞫有闲呈德夫","190845":"适江表","190602":"二月十六日感雨示同事","190844":"想庐山三首  其三","190601":"锁院深寂夭桃独芳有可怜之色为诗要德夫共赋以赏之","190843":"想庐山三首  其二","190600":"次韵和同时到院","190842":"想庐山三首  其一","190841":"宿坛石驿六首  其六","190840":"宿坛石驿六首  其五","190818":"登齐山","190817":"又过九华山","190816":"宿九华驿阻雨","190815":"阅九华录","190814":"冠帻峰","190813":"过九华山","190812":"姑熟州宅后泛舟清饮","190811":"李白祠堂","190819":"弄水亭","190810":"吴六合道原席上","190829":"建德道中感兴","190828":"对鉴","190827":"食鳜","190826":"过面山渡","190825":"即事","190824":"晓离杨梅驿","190823":"早行","190822":"宿杨梅驿","190821":"别滕元发侍郎","190820":"离池州过长围岭","190807":"泛滁河","190806":"夜宿淤丘","190805":"真守侯公辅见留之勤因辞以诗言欲遽往早还之意","190804":"和范子功学士留题二贤堂","190803":"赋牡丹黄虀","190802":"和社日小饮","190801":"陪秋叔游幽谷即席赋一川花","190800":"又用花字为即席","190809":"和徐仲元以诗见送","190808":"出滁口入江峡","190219":"棕花","190218":"得董都官书因为寄四首  其四","190217":"得董都官书因为寄四首  其三","190459":"再和范同年得厅字","190450":"睦州千峰榭二首  其一","190692":"又借前韵谢惠茶","190691":"和太守叔康以诗答桃","190690":"又借韵寄太守叔康","190216":"得董都官书因为寄四首  其二","190458":"劝元功饮","190215":"得董都官书因为寄四首  其一","190457":"呈范子镇同年","190699":"陈次全长春轩","190214":"独登临清阁","190456":"寒雨夜会得歌字","190698":"又和倒韵","190213":"又答惠诗并新鳝","190455":"检覆鸡啼源还虎峰","190697":"和雪三十韵","190212":"答鲁虞部见寄","190454":"题虎峰真师壁","190696":"和孙叔康寄示上元","190211":"贾庆甫示山中梅诗因继成","190453":"过法宁僧舍","190695":"孙太守席赋催妆","190210":"送浦大会甫赴榆次","190452":"宿广严靖阁","190694":"送王圣途得代还青社","190451":"睦州千峰榭二首  其二","190693":"寄橘柚","190229":"昨暮会饮庆甫署观女真花因求一二诺以厥明至期不至遂戏成一首","190228":"和贾尉女真花","190461":"涵碧亭","190460":"涵碧池","190227":"庆甫借棋子","190469":"席间和向辟之元夜  其一","190226":"和陶掾同登晓亭","190468":"和朱伯英元夕","190225":"枇杷","190467":"和朱尉示亲老生日","190224":"剪金花一首和陶掾","190466":"击瓯","190223":"观棋","190465":"双峰","190222":"乾元节口号","190464":"傲亭","190221":"榴花","190463":"双石鱼","190220":"和太守临清阁一首","190462":"瀑泉","190439":"自郡还寄长道","190438":"和太守郡阁望群山有雪","190437":"和朱伯英迓送还示","190679":"和孙叔康探梅二十八韵","190670":"和季春初牡丹花","190436":"初夏公余","190678":"和晚晴书事","190435":"和朱伯英后圃见招","190677":"和书怀","190434":"永康徐尉次寄颜令诗韵见寄因以前韵酬答","190676":"和登琅山为民祈福","190433":"县斋即事","190675":"和以双头牡丹赠叔康太守","190432":"寄长道","190674":"和木香花","190431":"观穑","190673":"和落花","190430":"和颜令见寄","190672":"和晚春雨霁","190671":"暮春对景书怀","190209":"贾尉见迫给廪因以诗戏","190208":"摄户纠二曹事因自戏","190207":"送李尉解任归庐陵","190449":"假道南康长道语今夕中秋正故岁聚并喜乐时也遂留以夜饮饮半和所示诗","190206":"和酬聂充甫新寄","190448":"中秋南康夜会得天字","190681":"和叔康席上  其一","190680":"和观雪二十韵","190205":"又和","190447":"伯瞻郎中生日","190689":"和孙叔康中秋寄运判胡秘丞","190204":"和聂充甫水南见寄","190446":"次韵和颜令见寄","190688":"和馀庆道中","190203":"思养","190445":"扫蒙亭","190687":"和凌霄花","190202":"对雨怀陶掾","190444":"和颜长道寄三首 阅武川倡酬","190686":"中夏偶成","190201":"和董都官登城南楼","190443":"和颜长道寄三首 县斋肆笔","190685":"和中夏清虚堂","190200":"初晴复雨感事","190442":"和颜长道寄三首 首夏","190684":"和潘通甫颐斋书事","190441":"谢朱伯英遗诗","190683":"哭路长吉","190440":"和颜长道见寄","190682":"和叔康席上  其二","190419":"和伯英初霁","190418":"和亭","190417":"闻诏士呈同僚朱伯英","190659":"和通甫道中先寄","190416":"离邑寄颜长道","190658":"和通甫见赠二首  其二","190415":"离石室","190657":"和通甫见赠二首  其一","190899":"水精笔架","190890":"偃盖松","190414":"途中寄县斋诸士子","190656":"送潘通甫沿牒淮东","190898":"灯花","190413":"村落","190655":"和潘通甫六月十二夜月","190897":"近元夕怀景纯少卿","190412":"将及熟溪","190654":"又和孙太守琅山席上","190896":"忆梅二首  其二","190411":"戏别颜令","190653":"琅山听窦山人琴","190895":"忆梅二首  其一","190410":"晓霁归邑","190652":"和孙叔康以诗寄芋","190894":"观飞雁偶十有三","190651":"和叔康侍亲游琅山  其二","190893":"感兴","190650":"和叔康侍亲游琅山  其一","190892":"海陵逢春","190891":"春晓","190429":"和朱尉见招","190428":"上睦州刘工部  其二","190427":"上睦州刘工部  其一","190669":"和潘通甫中春即事","190426":"试士毕同长道东归","190668":"又题僧壁即事","190425":"依前韵酬张屯田和诗","190667":"乙卯十二月十四日夜宿东禅僧舍","190424":"衢梁试院呈同事","190666":"廷评庆寿口号","190423":"权东阳既久求归武川上守倅 沈倅","190665":"寄邓舍人二首  其二","190422":"权东阳既久求归武川上守倅 章守","190664":"寄邓舍人二首  其一","190421":"和颜令见寄  其二","190663":"寄孙叔康","190420":"和颜令见寄  其一","190662":"和潘通甫陈贴港道中作","190661":"和潘通甫寄孙太守","190660":"和通甫同登庆和寺阁","190639":"小雪后牡丹号朝天红者开于县宅西圃","190638":"再和颜长道见寄","190637":"游齐州灵岩四首  其四","190879":"琅邪三十二咏 千佛塔","190636":"游齐州灵岩四首  其三","190878":"琅邪三十二咏 大历井","190635":"游齐州灵岩四首  其二","190877":"琅邪三十二咏 清风亭","190634":"游齐州灵岩四首  其一","190876":"琅邪三十二咏 归云洞","190633":"路疑  其二","190875":"琅邪三十二咏 招隐堂","190632":"路疑  其一","190874":"琅邪三十二咏 寂乐亭","190631":"和孙正甫二首  其二","190873":"琅邪三十二咏 酴醾轩","190630":"和孙正甫二首  其一","190872":"琅邪三十二咏 白龙泉","190871":"琅邪三十二咏 庶子泉","190870":"琅邪三十二咏 阳冰篆","190409":"雨止","190408":"鸡人峰","190407":"冒雨游石室","190649":"和潘通甫芍药","190406":"自灵岩回途中寄颜令","190648":"和孙叔康九日三首  其三","190405":"宿灵岩  其二","190647":"和孙叔康九日三首  其二","190889":"栩栩亭","190404":"宿灵岩  其一","190646":"和孙叔康九日三首  其一","190888":"客舍早春","190403":"望方岩","190645":"暑雨言怀和潘倅十八韵","190887":"琅邪三十二咏 东峰亭","190402":"下山复题二首  其二","190644":"和潘通甫芍药十韵","190886":"琅邪三十二咏 法华池","190401":"下山复题二首  其一","190643":"喜潘通甫回郡","190885":"琅邪三十二咏 会峰亭","190400":"游寿山","190642":"按水旱之灾将毕呈叔康太守","190884":"琅邪三十二咏 石屏风","190641":"寄橙与孙叔康","190883":"琅邪三十二咏 望日台","190640":"八月二十四日州牡丹","190882":"琅邪三十二咏 了了堂","190881":"琅邪三十二咏 晓光亭","190880":"琅邪三十二咏 石庵","190175":"行役一首","190174":"武夷游仙咏","190173":"喜雨和曹子方","190172":"和苏进之同游乌奴山告成寺","190171":"过龙洞","190170":"石鏊","190179":"留题忠州丰都景德观","190178":"和孔彦常侍郎癸酉冬雪","190177":"和礼部苏尚书穉栝","190176":"别李世美","190186":"上太守陈少卿十韵","190185":"陪宜春守皮献臣游化成岩","190184":"谗龙","190183":"八月十八日观潮","190182":"杨内翰读书堂","190181":"追咏西园海棠","190180":"岑公洞","190189":"和闻新制间岁贡士","190188":"答董都官索去年诗债","190187":"董都官索署中山亭诗","190153":"过婺源诸岭","190395":"县圃刈禾","190152":"九日凤凰寺","190394":"闻国哀","190151":"月岩","190393":"还邑遇雨","190150":"上饶祥符寺山亭","190392":"石龙","190391":"野塘白莲","190390":"离邑之衢按狱","190159":"求陈和叔草书千文","190158":"观江都王画拳毛䯄","190157":"题君佐寓翁庵","190399":"过紫霄宫","190156":"寒菊","190398":"同邑簿检视堤柳乘兴游保寿僧舍","190155":"中和堂","190397":"答颜长道见寄","190154":"古金章","190396":"答吕秀才","190164":"谢郑州张资政惠书寄酥十四韵","190163":"和彦常看月","190162":"昨日辄以鄙句奉谢重辱长篇为贶再藉来韵和答次韵","190161":"暮夜还家得清叟所留二诗因以谢","190160":"谢中书张侍郎分惠赐冰","190169":"石柜阁","190168":"百堂寺","190167":"得鹿","190166":"小仲渡","190165":"之文","190131":"送皮献臣郎中赴河朔","190373":"咏唐史 邓景山","190130":"和邓舍人读之罘碑二十韵","190372":"咏唐史 李光弼","190371":"咏唐史 契苾何力","190370":"咏唐史 韦见素","190139":"和新晴","190138":"□□□","190137":"和待梅花从一字至十字句","190379":"咏唐史 萧复","190136":"复用前韵谢和鄙篇以送行县","190378":"咏唐史 郭子仪","190135":"即席","190377":"咏唐史 杨绾","190134":"赋金橘得曲字","190376":"咏唐史 崔荛","190133":"和残腊幽谷西游适","190375":"咏唐史 房琯","190132":"观劈石","190374":"咏唐史 韦坚","190142":"饮樱桃园","190384":"石龟","190141":"和留春亭席上送苏判官","190383":"送刘诚夫江阴狱掾","190140":"早春游王氏园看牡丹约花开再游探韵赋诗得早字","190382":"忆双栟榈","190381":"咏唐史 李揆","190380":"咏唐史 柳浑","190149":"石井泉","190148":"鹅湖仁寿寺","190147":"宿景德方丈","190389":"登楼","190146":"晓雨离铜山驿","190388":"金华按覆回止普净","190145":"赋酴醾短歌少留行旆","190387":"雨池荷花","190144":"新泉","190386":"喜德甫彦文至","190143":"州宅牡丹盛开蒙剪栏中奇品见赠仍属为短歌于席上","190385":"县斋即事","190119":"寄云门运禅师","190118":"雨霁剡谿","190351":"石夫人挽辞","190593":"宿新乐驿","190350":"千佛岩读书寄内","190592":"行年","190591":"和孙世则著作新年见寄  其二","190590":"和孙世则著作新年见寄  其一","190117":"句","190359":"咏唐史 二阎","190116":"菊花诗问答  其二","190358":"咏唐史 李适之","190115":"菊花诗问答  其一","190357":"咏唐史 张中令","190599":"赣州鞫劾呈同事邓宰德夫","190114":"句","190356":"咏唐史 李朝隐","190598":"寒食","190113":"望江亭","190355":"咏唐史 尹思正","190597":"南昌鐡柱","190112":"句  其三","190354":"咏唐史 李英公","190596":"喜晴","190111":"句  其二","190353":"咏唐史 李卫公","190595":"安福驿","190110":"句  其一","190352":"石经老挽辞","190594":"之虔推劾道远雨甚念从隶之劳","190129":"句","190120":"再寄云门运禅师","190362":"咏唐史 卢怀慎","190361":"咏唐史 刘知几","190360":"咏唐史 苏世长","190128":"石潭院次蟾禅师韵","190127":"过灵泉寺  其四","190369":"咏唐史 虞世南","190126":"过灵泉寺  其三","190368":"咏唐史 魏郑公","190125":"过灵泉寺  其二","190367":"咏唐史 戴至德","190124":"过灵泉寺  其一","190366":"咏唐史 戴胄","190123":"留题洪庆观","190365":"咏唐史 王珪","190122":"劝学","190364":"咏唐史 杨国忠","190121":"调王辟之","190363":"咏唐史 李林甫","190197":"杂咏五首  其五","190196":"杂咏五首  其四","190195":"杂咏五首  其三","190194":"杂咏五首  其二","190193":"杂咏五首  其一","190192":"和寒食","190191":"和久雨","190190":"和江亭春半","190199":"清明闻楚歌","190198":"惜花","190739":"坐中闻击鼓殴傩声戏联数韵","190738":"和雪意","190737":"和腊日初晴会同僚射饮投壶","190979":"送冯材叔宰蕲春","190736":"和山郡早起  其二","190978":"京居","190735":"和山郡早起  其一","190977":"和中裕古鉴","190734":"幽谷回口占呈和叔内翰","190976":"和吴子友贡院作","190733":"又和","190975":"寄陈君佐","190732":"和喜奉御札改元元丰口号","190974":"和久中春风","190731":"和会峰亭","190973":"又次前韵答所和诗","190730":"雪后游琅邪山联句","190972":"戏呈吴伯固同年","190971":"和达夫雪霁","190970":"和久中闻笛","190509":"内乐亭","190508":"钧爱亭","190507":"和东美见寄","190749":"和柳眼","190506":"和东美示内乐亭诗","190748":"和野步","190505":"试罢","190747":"和因观罩鱼斫鲙  其二","190989":"又和彦常试院即事  其三","190504":"呈孙东美","190746":"和因观罩鱼斫鲙  其一","190988":"又和彦常试院即事  其二","190503":"效谢宣城体呈同事","190745":"和天庆观醮宿","190987":"又和彦常试院即事  其一","190502":"将归","190744":"和岁节见招城上闲步","190986":"较试将毕呈彦衡察院上官","190501":"再和","190743":"元丰改元元日登行春阁","190985":"又和前韵呈彦常明叔","190500":"和朱伯英以诗庆将代","190742":"和岁除","190984":"又和","190741":"和郡斋即事","190983":"同文馆试上舍和同事孔彦常学士即事","190740":"行县坐野馆食次得所贶手墨兼惠雀鲊兔馔因以鄙句驰谢","190982":"致政孙大夫挽词","190981":"邃明生日","190980":"韩敏之学士贰少府往拜凡三而未觏因致以诗","190719":"和陈和叔内翰忆梅花因手植数本又命画工作生枝于屏间","190718":"介亭二十韵呈杭守祖龙图","190717":"次韵和孙世则以诗送别","190959":"陈公武中散生日","190716":"和叔康首夏书怀五首  其五","190958":"留别张枢言龙图二首  其二","190715":"和叔康首夏书怀五首  其四","190957":"留别张枢言龙图二首  其一","190714":"和叔康首夏书怀五首  其三","190956":"石懿老大夫生日","190713":"和叔康首夏书怀五首  其二","190955":"舟次柳子小饮呈成伯学士","190712":"和叔康首夏书怀五首  其一","190954":"再和陈成伯见寄集句三首","190711":"谢通甫寄交藤方并气术图","190953":"再和","190710":"和金沙道中晚景","190952":"和陈成伯小饮","190951":"惜花","190950":"离丹阳","190729":"辞劝饮","190728":"和夜登东阁","190727":"和闲步城上率游城南","190969":"示黄彦发欧阳勉甫道旧","190726":"明月庵","190968":"又和锁宿即事","190725":"和雪前数刻迎郊赦口占","190967":"次韵杨久中将试进士","190724":"咏雪霁月夜见简","190966":"和赵达夫元夕礼闱锁宿","190723":"咏雪","190965":"又和来篇","190722":"次韵和同游溪北竹园","190964":"再和答篇","190721":"次韵答和叔见招茅庵弈棋","190963":"迁居近局谢陈成伯假车惠茶","190720":"丛山堂","190962":"中书张侍郎生日","190961":"送范子镇承议同年宰清源","190960":"过金陵上仆射王舒公","190939":"又和九日有怀见寄","190938":"和温伯道旧见寄","190937":"用别韵再和","190936":"和邓温伯内翰九月七日约游北高峰","190935":"送周开祖赴阙引对","190934":"又和仲远答锐长老二首  其二","190933":"又和仲远答锐长老二首  其一","190932":"和仲远留题方锐长老方丈","190931":"蔡仲远内翰出虢州刘龙图所寄诗因次其韵","190930":"将归","190708":"和潘倅通甫游狼山寺三首  其三","190707":"和潘倅通甫游狼山寺三首  其二","190949":"劝酒","190706":"和潘倅通甫游狼山寺三首  其一","190948":"和丹阳守许仲途朝议春深饮会即席二首  其二","190705":"蒜山酒","190947":"和丹阳守许仲途朝议春深饮会即席二首  其一","190704":"昨日以事不得陪赴和甫学士之召","190946":"和见寄","190703":"京口别叔康","190945":"次韵答所和","190702":"复用叔康送篇韵和答","190944":"汴上简陈成伯学士","190701":"别叔康","190943":"胡巨源郎中挽词三首  其三","190709":"和行海门","190700":"太守孙叔康下车","190942":"胡巨源郎中挽词三首  其二","190941":"胡巨源郎中挽词三首  其一","190940":"致政孙朝请过故里为五老之会","190917":"咏烟","190916":"访隐","190915":"方竹杖","190914":"陈后主","19089":"次韵徐庭珍春日杂言十首  其七","190913":"咏声","19088":"次韵徐庭珍春日杂言十首  其六","190912":"咏影","190911":"雕狐图","190910":"花鐡书镇","19085":"次韵徐庭珍春日杂言十首  其三","19084":"次韵徐庭珍春日杂言十首  其二","19087":"次韵徐庭珍春日杂言十首  其五","19086":"次韵徐庭珍春日杂言十首  其四","19081":"再次韵  其一","19080":"岩桂饷郑舜举戏笔代柬  其二","19083":"次韵徐庭珍春日杂言十首  其一","190919":"探后园桃花二首  其二","19082":"再次韵  其二","190918":"探后园桃花二首  其一","19090":"次韵徐庭珍春日杂言十首  其八","190928":"春思五首  其五","190927":"春思五首  其四","190926":"春思五首  其三","190925":"春思五首  其二","190924":"春思五首  其一","190923":"又和灯夕见寄","190922":"和吕景纯以梅花盛开见寄","190921":"多景楼","19096":"李倅生辰三首  其一","19095":"次韵陈季陵元夕  其三","19098":"李倅生辰三首  其三","19097":"李倅生辰三首  其二","19092":"次韵徐庭珍春日杂言十首  其一○","19091":"次韵徐庭珍春日杂言十首  其九","19094":"次韵陈季陵元夕  其二","190929":"春游","19093":"次韵陈季陵元夕  其一","190920":"溪上桃","190339":"周生哀辞","190338":"杜鹃","190571":"岳阳楼","190570":"君山","190337":"即事","190579":"金精岩","190336":"病目未愈","190578":"安远道中","190335":"阻雨","190577":"送周广之令桂阳","190334":"清明","190576":"送潘簿还侍下","190333":"陪胡公弈棋","190575":"和朱伯英新州诗见寄二首  其二","190332":"忆富川四首  其四","190574":"和朱伯英新州诗见寄二首  其一","190331":"忆富川四首  其三","190573":"阅金科","190330":"忆富川四首  其二","190572":"晓起","190109":"白石洞天","190108":"集真观","190107":"净名院  其二","190349":"忆江上","190340":"致政胡郎中生日","190582":"中秋午夜和溪看月","190581":"板石驿","190580":"游金精回书朝阳岩观壁","190106":"净名院  其一","190348":"去年今日","190105":"云岩禅寺","190347":"赠项子后处士","190589":"至万安","190104":"白石山  其二","190346":"简夫丈昔遗老杜别集而骧以外集当之久而亡去近承多本因以诗请","190588":"九月八日薄晚离赣城十余里而雷雨作遂倚舟以宿九日晓行又十余里而逆风暴甚乃泊于白鹇滩侧虔之史君相留不可屡以亟行见谑今日会宾席间当语及濡滞以为笑矣因书以自戏云","190103":"白石山  其一","190345":"送处道丈之台任民掾","190587":"九月八日离虔","190102":"箫台山","190344":"和扑满","190586":"天柱滩","190101":"羞墓诗","190343":"又和闲居","190585":"过赣石","190100":"访慧山钱道人不遇","190342":"又和见招鼓山游","190584":"登欎孤台  其二","190341":"和简夫游南岩","190583":"登欎孤台  其一","190319":"舍绮霞阁五首呈石丈职方 水中亭","190318":"舍绮霞阁五首呈石丈职方 绮霞阁","190317":"陶令祠","190559":"寄上高宰孙世则","190316":"狄公祠","190558":"刘仲诚以武夷记见借","190791":"偶疾未平不得预龙蟠之游辄成诗以迓还旆","190790":"再和  其二","190315":"庾楼","190557":"和龚簿同辨金剑源","190799":"赋迎赏欲开杏花得花字","190314":"过白公堂","190556":"送章少卿赴阙","190798":"和苏正甫劝饮之作","190313":"南湖晚霁","190555":"寄题吉州三瑞堂","190797":"席上劝仲元著作勿辞酒","190312":"代官未至泊舟颁条门独宿署中","190554":"陪吉守范淳元观玉虚观灵芝席上口占","190796":"元日","190311":"闻诏寄鲁成之兄弟","190553":"又和来篇","190795":"和耿天隲翦彩梅花得开字","190310":"答鲁成之兄弟以诗惠牡丹","190552":"赠别伯升","190794":"送别回作","190551":"中秋夜","190793":"饯别劝饮","190550":"庐陵待试士呈伯升郎中","190792":"牙城话别口占","190329":"忆富川四首  其一","190328":"初睡","190327":"得陈安道书知移邑名次","190569":"洞庭即事  其二","190560":"道中寄景升仲诚二同官","190326":"遣兴一绝","190568":"洞庭即事  其一","190325":"贺简夫石丈罢令先期请老","190567":"寄示二小子","190324":"待令移寓赵氏园亭","190566":"洞庭秋四首  其四","190323":"和石丈职方长春花","190565":"洞庭秋四首  其三","190322":"舍绮霞阁五首呈石丈职方 小山","190564":"洞庭秋四首  其二","190321":"舍绮霞阁五首呈石丈职方 蕉迳","190563":"洞庭秋四首  其一","190320":"舍绮霞阁五首呈石丈职方 枯荷","190562":"巴陵讯囚所居附岳阳楼前  其二","190561":"巴陵讯囚所居附岳阳楼前  其一","190539":"离泗上","190538":"无脚桥","190537":"再回前韵","190779":"和樱桃花开账饮口占","190536":"至泗即天长独归叙别照邻","190778":"幽谷谢惠新酿家馔奉亲","190535":"延和引对","190777":"茅亭观雨中杏花得中字","190534":"汴舟早行二首  其二","190776":"和野步自幽谷之寺庄","190533":"汴舟早行二首  其一","190775":"画舫泛春偶联一绝","190532":"送郭照邻赴南雄签幕","190774":"和城头相望","190531":"附郭照邻舟还乡一首","190773":"和答代简二绝  其二","190530":"七夕寄安道","190772":"和答代简二绝  其一","190771":"雨后城上种蜀葵效辘轳体联句","190770":"和观新历  其二","190309":"董公肃都官被命倅南海以当分符之寄南归道中贶书因以诗为寄一首","190308":"迎亲来毕幼妹之嫁久雨稽阻思望而作一首","190307":"和鲁成之兄弟见谢","190549":"和简夫送信臣同年","190306":"感事","190548":"又和","190305":"田叔","190547":"和信臣游简夫太丞申园","190789":"再和  其一","190780":"又和行字二韵","190304":"辨诈","190546":"简夫丈约游南岩时以妇翁室会遂渝爽依韵和其来篇","190788":"和山行回坐临清桥啜茶","190303":"夜射通叔虞曹圃","190545":"和南岩回","190787":"再和前韵仍以峨字为首尾","190302":"晓坐","190544":"答信臣遗诗以失南岩约","190786":"倒用前韵","190301":"十月暮登延寿阁","190543":"和李信臣游南岩","190785":"和会饮牡丹丛间","190300":"宣赦回马上口占","190542":"申园席上口占","190784":"和小雨乘兴游城西竹园","190541":"和简夫游鼓山","190783":"又和至丛山堂口占","190540":"避雨大明寺","190782":"和春晚过幽谷口占","190781":"和正闰晦日","190519":"题周开祖丛翠轩","190518":"平望阻风","190517":"过千金怀陆刚叔许顾道","190759":"和新晴","190516":"离乡","190758":"和春阴倦游","190515":"国哀","190757":"和适意","190514":"木芙蓉词","190756":"上元后南溪泛舟联句","190513":"凌翠阁  其四","190755":"和山城灯夜","190512":"凌翠阁  其三","190754":"和立春日东风雪意偶作","190511":"凌翠阁  其二","190753":"和宝严阁","190510":"凌翠阁  其一","190752":"竹径","190751":"和见招","190750":"小桧球","190529":"七夕","190528":"又和所示","190527":"寄陈安道","190769":"和观新历  其一","190526":"岩斋晓起","190768":"滁上闲日阴晴联句","190525":"和黄彦文示诗","190767":"赋石棋子以机字韵","190524":"予枕屏书叔夜养生论而孙楚材观之有诗相示遂次来韵以答","190766":"再和春寒次来韵","190523":"宿零壁驿","190765":"以前韵作春寒攀迓","190522":"早行","190764":"迎春花","190521":"再和所酬","190763":"赋新笋","190520":"汴上遇孙楚材","190762":"和见招游城东园","190761":"谢惠山花菜","190760":"谢惠瓦墩"}
